LICENSE.txt
README.md
pyproject.toml
setup.py
uast/__init__.py
uast/__version__.py
uast.egg-info/PKG-INFO
uast.egg-info/SOURCES.txt
uast.egg-info/dependency_links.txt
uast.egg-info/entry_points.txt
uast.egg-info/top_level.txt
uast/cli/__init__.py
uast/cli/cli.py
uast/cli/parser.py
uast/core/__init__.py
uast/core/ast_parsers.py
uast/core/parser.py
uast/core/containers/__init__.py
uast/core/containers/containers.py
uast/core/containers/containers_mixin.py