Metadata-Version: 2.1
Name: uast
Version: 0.0.0
Summary: Uast, user abstract syntax tree, is a
Home-page: https://github.com/VascoSch92/uast
Author: Vasco Schiavo
Author-email: vasco.schiavo@protonmail.com
License: MIT
Keywords: structure,testing,schema,syntax
Classifier: Development Status :: 5 - Production/Stable
Classifier: Intended Audience :: Education
Classifier: Intended Audience :: End Users/Desktop
Classifier: Intended Audience :: Science/Research
Classifier: License :: OSI Approved :: MIT License
Classifier: Programming Language :: Python :: 3.9
Classifier: Programming Language :: Python :: 3.10
Classifier: Programming Language :: Python :: 3.11
Classifier: Programming Language :: Python :: 3.12
Requires-Python: >=3.9
License-File: LICENSE.txt
